MANIFEST.in
readme.rst
setup.py
ysmtool/__init__.py
ysmtool/aizhan.py
ysmtool/baidu.py
ysmtool/haosou.py
ysmtool/http.py
ysmtool/tool.py
ysmtool.egg-info/PKG-INFO
ysmtool.egg-info/SOURCES.txt
ysmtool.egg-info/dependency_links.txt
ysmtool.egg-info/requires.txt
ysmtool.egg-info/top_level.txt
ysmtool.egg-info/zip-safe