Metadata-Version: 1.0
Name: ysmtool
Version: 0.9
Summary: 个人工具库，主要用于SEO，数据采集方面
Home-page: http://www.yesiming.com
Author: simon
Author-email: simon@yesiming.com
License: UNKNOWN
Platform: UNKNOWN
